nutrition_lib/__init__.py
nutrition_lib/nutrition.py
nutrition_lib-0.1.0.dist-info/METADATA
nutrition_lib-0.1.0.dist-info/WHEEL
nutrition_lib-0.1.0.dist-info/top_level.txt
nutrition_lib-0.1.0.dist-info/RECORD
