Metadata-Version: 2.1
Name: nutrition-lib
Version: 0.1.0
Summary: A simple nutrition tracking library
Home-page: https://github.com/yourusername/nutrition_tracker
Author: Akhila Kandadi
Author-email: akhilareddykandadi@gmail.com
License: UNKNOWN
Platform: UNKNOWN
Classifier: Programming Language :: Python :: 3
Classifier: License :: OSI Approved :: MIT License
Classifier: Operating System :: OS Independent
Requires-Python: >=3.6
